py_hurlenko_fileserver/__init__.py
py_hurlenko_fileserver/actions.py
py_hurlenko_fileserver/auth.py
py_hurlenko_fileserver/py.typed
py_hurlenko_fileserver-0.1.3.dist-info/METADATA
py_hurlenko_fileserver-0.1.3.dist-info/WHEEL
py_hurlenko_fileserver-0.1.3.dist-info/RECORD
