Metadata-Version: 2.4
Name: py-hurlenko-fileserver
Version: 0.1.3
Summary: Add your description here
Author-email: dockerdavid <jdgomezdelgado@uts.edu.co>
Requires-Python: >=3.13
Requires-Dist: aiohttp>=3.11.18
